{"nodes": [{"id": "src_lib_editor_scene_block_svelte_ts", "label": "scene-block.svelte.ts", "file_type": "code", "source_file": "src\\lib\\editor\\scene-block.svelte.ts", "source_location": "L1"}], "edges": [{"source": "src_lib_editor_scene_block_svelte_ts", "target": "core", "relation": "imports_from", "confidence": "EXTRACTED", "source_file": "src\\lib\\editor\\scene-block.svelte.ts", "source_location": "L2", "weight": 1.0}, {"source": "src_lib_editor_scene_block_svelte_ts", "target": "svelte", "relation": "imports_from", "confidence": "EXTRACTED", "source_file": "src\\lib\\editor\\scene-block.svelte.ts", "source_location": "L3", "weight": 1.0}, {"source": "src_lib_editor_scene_block_svelte_ts", "target": "sceneblockview_svelte", "relation": "imports_from", "confidence": "EXTRACTED", "source_file": "src\\lib\\editor\\scene-block.svelte.ts", "source_location": "L4", "weight": 1.0}], "raw_calls": []}